LICENSE
README.md
setup.py
terraform.py
terraform_binaryi_wrapper.egg-info/PKG-INFO
terraform_binaryi_wrapper.egg-info/SOURCES.txt
terraform_binaryi_wrapper.egg-info/dependency_links.txt
terraform_binaryi_wrapper.egg-info/entry_points.txt
terraform_binaryi_wrapper.egg-info/top_level.txt