Metadata-Version: 2.1
Name: terraform-binaryi-wrapper
Version: 1.0.2.post1
Summary: Python wrapper for Terraform
Home-page: https://github.com/imanazari70/terraform-binary-wrapper
Author: Iman Azari
Author-email: azari@mahsan.co
License: UNKNOWN
Platform: UNKNOWN
License-File: LICENSE
